[
  {
    "title": "Snake Modern",
    "filename": "snake.py",
    "category": "CLASSIC",
    "description": "Classic snake game with modern sleek design and smooth animations",
    "builtin": true,
    "playable": true,
    "rating": 4.5,
    "icon": "🐍"
  },
  {
    "title": "Tetris Modern",
    "filename": "tetris.py", 
    "category": "PUZZLE",
    "description": "Block puzzle game with contemporary UI and theme switching",
    "builtin": true,
    "playable": true,
    "rating": 4.8,
    "icon": "🧩"
  },
  {
    "title": "Pong Modern",
    "filename": "pong.py", 
    "category": "ARCADE",
    "description": "Two-player classic reimagined with modern physics and AI",
    "builtin": true,
    "playable": true,
    "rating": 4.2,
    "icon": "🏓"
  },
  {
    "title": "Breakout Modern",
    "filename": "breakout.py",
    "category": "ARCADE", 
    "description": "Break all bricks with power-ups and modern particle effects",
    "builtin": true,
    "playable": true,
    "rating": 4.6,
    "icon": "🧱"
  }
]